getuipy/BatchImpl.py
getuipy/GtConfig.py
getuipy/RequestException.py
getuipy/__init__.py
getuipy/alias_demo.py
getuipy/demo.py
getuipy/igt_push.py
getuipy/google/__init__.py
getuipy/google/protobuf/__init__.py
getuipy/google/protobuf/any_pb2.py
getuipy/google/protobuf/any_test_pb2.py
getuipy/google/protobuf/api_pb2.py
getuipy/google/protobuf/descriptor.py
getuipy/google/protobuf/descriptor_database.py
getuipy/google/protobuf/descriptor_pb2.py
getuipy/google/protobuf/descriptor_pool.py
getuipy/google/protobuf/duration_pb2.py
getuipy/google/protobuf/empty_pb2.py
getuipy/google/protobuf/field_mask_pb2.py
getuipy/google/protobuf/json_format.py
getuipy/google/protobuf/map_proto2_unittest_pb2.py
getuipy/google/protobuf/map_unittest_pb2.py
getuipy/google/protobuf/message.py
getuipy/google/protobuf/message_factory.py
getuipy/google/protobuf/proto_builder.py
getuipy/google/protobuf/reflection.py
getuipy/google/protobuf/service.py
getuipy/google/protobuf/service_reflection.py
getuipy/google/protobuf/source_context_pb2.py
getuipy/google/protobuf/struct_pb2.py
getuipy/google/protobuf/symbol_database.py
getuipy/google/protobuf/test_messages_proto2_pb2.py
getuipy/google/protobuf/test_messages_proto3_pb2.py
getuipy/google/protobuf/text_encoding.py
getuipy/google/protobuf/text_format.py
getuipy/google/protobuf/timestamp_pb2.py
getuipy/google/protobuf/type_pb2.py
getuipy/google/protobuf/unittest_arena_pb2.py
getuipy/google/protobuf/unittest_custom_options_pb2.py
getuipy/google/protobuf/unittest_import_pb2.py
getuipy/google/protobuf/unittest_import_public_pb2.py
getuipy/google/protobuf/unittest_mset_pb2.py
getuipy/google/protobuf/unittest_mset_wire_format_pb2.py
getuipy/google/protobuf/unittest_no_arena_import_pb2.py
getuipy/google/protobuf/unittest_no_arena_pb2.py
getuipy/google/protobuf/unittest_no_generic_services_pb2.py
getuipy/google/protobuf/unittest_pb2.py
getuipy/google/protobuf/unittest_proto3_arena_pb2.py
getuipy/google/protobuf/wrappers_pb2.py
getuipy-0.0.1.dist-info/LICENSE
getuipy-0.0.1.dist-info/METADATA
getuipy-0.0.1.dist-info/WHEEL
getuipy-0.0.1.dist-info/top_level.txt
getuipy-0.0.1.dist-info/RECORD
