Metadata-Version: 2.1
Name: getuipy
Version: 0.0.1
Summary: Not an official Getui SDK
Home-page: https://github.com/lbhsot/getuipy.git
Author: Samuel Lee
Author-email: samuelx082@gmail.com
License: UNKNOWN
Platform: UNKNOWN
Classifier: Programming Language :: Python :: 3
Classifier: License :: OSI Approved :: MIT License
Classifier: Operating System :: OS Independent
